rub.py
rub-0.0.0.dist-info/COPYING
rub-0.0.0.dist-info/WHEEL
rub-0.0.0.dist-info/METADATA
rub-0.0.0.dist-info/RECORD
