Metadata-Version: 2.1
Name: rub
Version: 0.0.0
Summary: A static generator
Keywords: ssg,feed,markdown
Author-email: Nguyễn Gia Phong <mcsinyx@disroot.org>
Maintainer-email: Nguyễn Gia Phong <mcsinyx@disroot.org>
Requires-Python: >=3.7
Classifier: Development Status :: 1 - Planning
Classifier: License :: OSI Approved :: GNU Affero General Public License v3 or later (AGPLv3+)
Classifier: Operating System :: OS Independent
Classifier: Programming Language :: Python
Classifier: Topic :: Utilities
Requires-Dist: markdown-it-py
Project-URL: SourceHut, https://sr.ht/~cnx/rub
